iconservice/__init__.py
iconservice/__main__.py
iconservice/__version__.py
iconservice/dosguard.py
iconservice/icon_config.py
iconservice/icon_constant.py
iconservice/icon_inner_service.py
iconservice/icon_service.py
iconservice/icon_service_cli.py
iconservice/icon_service_engine.py
iconservice/precommit_data_manager.py
iconservice/base/ComponentBase.py
iconservice/base/__init__.py
iconservice/base/address.py
iconservice/base/block.py
iconservice/base/exception.py
iconservice/base/message.py
iconservice/base/transaction.py
iconservice/base/type_converter.py
iconservice/base/type_converter_templates.py
iconservice/builtin_scores/__init__.py
iconservice/builtin_scores/governance/__init__.py
iconservice/builtin_scores/governance/governance.py
iconservice/builtin_scores/governance/package.json
iconservice/builtin_scores/system/__init__.py
iconservice/builtin_scores/system/package.json
iconservice/builtin_scores/system/system.py
iconservice/database/__init__.py
iconservice/database/batch.py
iconservice/database/db.py
iconservice/database/factory.py
iconservice/database/wal.py
iconservice/deploy/__init__.py
iconservice/deploy/engine.py
iconservice/deploy/icon_score_deployer.py
iconservice/deploy/storage.py
iconservice/deploy/utils.py
iconservice/fee/__init__.py
iconservice/fee/deposit.py
iconservice/fee/deposit_meta.py
iconservice/fee/engine.py
iconservice/fee/storage.py
iconservice/iconscore/__init__.py
iconservice/iconscore/db.py
iconservice/iconscore/icon_container_db.py
iconservice/iconscore/icon_pre_validator.py
iconservice/iconscore/icon_score_api_generator.py
iconservice/iconscore/icon_score_base.py
iconservice/iconscore/icon_score_base2.py
iconservice/iconscore/icon_score_constant.py
iconservice/iconscore/icon_score_context.py
iconservice/iconscore/icon_score_context_util.py
iconservice/iconscore/icon_score_engine.py
iconservice/iconscore/icon_score_event_log.py
iconservice/iconscore/icon_score_mapper.py
iconservice/iconscore/icon_score_mapper_object.py
iconservice-1.9.1.dist-info/METADATA
iconservice-1.9.1.dist-info/WHEEL
iconservice-1.9.1.dist-info/entry_points.txt
iconservice-1.9.1.dist-info/top_level.txt
iconservice-1.9.1.dist-info/RECORD
