Metadata-Version: 2.1
Name: iconservice
Version: 1.9.1
Summary: ICON Service for Python
Home-page: https://github.com/icon-project/icon-service
Author: ICON Foundation
Author-email: foo@icon.foundation
License: Apache License 2.0
Platform: UNKNOWN
Classifier: Development Status :: 5 - Production/Stable
Classifier: Intended Audience :: Developers
Classifier: Intended Audience :: System Administrators
Classifier: Natural Language :: English
Classifier: License :: OSI Approved :: Apache Software License
Classifier: Programming Language :: Python :: 3.7
Requires-Python: >=3.7, <3.8
Requires-Dist: setproctitle (~=1.1.10)
Requires-Dist: plyvel (~=1.2.0)
Requires-Dist: coincurve (~=13.0.0)
Requires-Dist: earlgrey (~=0.2.1)
Requires-Dist: iconcommons (~=1.1.3)
Requires-Dist: msgpack (~=1.0.0)
Requires-Dist: iso3166 (~=1.0.1)
Requires-Dist: typing-extensions (~=3.7.4)
Provides-Extra: test
Requires-Dist: hypothesis (>=4.0.0) ; extra == 'test'
Requires-Dist: pytest (>=3.6) ; extra == 'test'
Requires-Dist: pytest-cov (>=2.5.1) ; extra == 'test'
Requires-Dist: iconsdk ; extra == 'test'
Requires-Dist: pytest-mock ; extra == 'test'
